simpletkgui/__init__.py
simpletkgui/simpleapp.py
simpletkgui/simpleconfig.py
simpletkgui/simpleicons.py
simpletkgui/simplestyles.py
simpletkgui/simpleviews.py
simpletkgui/simplewidgets.py
simpletkgui-1.1.2.dist-info/LICENSE
simpletkgui-1.1.2.dist-info/METADATA
simpletkgui-1.1.2.dist-info/WHEEL
simpletkgui-1.1.2.dist-info/top_level.txt
simpletkgui-1.1.2.dist-info/RECORD
