Metadata-Version: 2.1
Name: simpletkgui
Version: 1.1.2
Summary: A collection of tools wrapped around tkinter to make good-looking GUIs quickly
Home-page: https://github.com/michael-genson/simpletkgui
Author: Michael Genson
Author-email: genson.michael@gmail.com
License: MIT
Platform: UNKNOWN
